odoo/addons/crm_location_nuts/README.rst
odoo/addons/crm_location_nuts/__init__.py
odoo/addons/crm_location_nuts/__manifest__.py
odoo/addons/crm_location_nuts/i18n/bg.po
odoo/addons/crm_location_nuts/i18n/crm_location_nuts.pot
odoo/addons/crm_location_nuts/i18n/de.po
odoo/addons/crm_location_nuts/i18n/es.po
odoo/addons/crm_location_nuts/i18n/fr.po
odoo/addons/crm_location_nuts/i18n/hr.po
odoo/addons/crm_location_nuts/i18n/it.po
odoo/addons/crm_location_nuts/i18n/pt_BR.po
odoo/addons/crm_location_nuts/i18n/sk.po
odoo/addons/crm_location_nuts/i18n/sl.po
odoo/addons/crm_location_nuts/i18n/tr.po
odoo/addons/crm_location_nuts/i18n/zh_CN.po
odoo/addons/crm_location_nuts/models/__init__.py
odoo/addons/crm_location_nuts/models/crm_lead.py
odoo/addons/crm_location_nuts/readme/CONTRIBUTORS.rst
odoo/addons/crm_location_nuts/readme/CREDITS.rst
odoo/addons/crm_location_nuts/readme/DESCRIPTION.rst
odoo/addons/crm_location_nuts/readme/ROADMAP.rst
odoo/addons/crm_location_nuts/readme/USAGE.rst
odoo/addons/crm_location_nuts/static/description/icon.png
odoo/addons/crm_location_nuts/static/description/index.html
odoo/addons/crm_location_nuts/tests/__init__.py
odoo/addons/crm_location_nuts/tests/test_crm_location_nuts.py
odoo/addons/crm_location_nuts/views/crm_lead_view.xml
odoo_addon_crm_location_nuts-16.0.1.0.0.4.dist-info/METADATA
odoo_addon_crm_location_nuts-16.0.1.0.0.4.dist-info/WHEEL
odoo_addon_crm_location_nuts-16.0.1.0.0.4.dist-info/top_level.txt
odoo_addon_crm_location_nuts-16.0.1.0.0.4.dist-info/RECORD
